odoo_kernel_launcher.py
odoo_wsgi_cli.py
odoo_wsgi/.env
odoo_wsgi/__init__.py
odoo_wsgi/__main__.py
odoo_wsgi/dispatch.py
odoo_wsgi/monkey_patch.py
odoo_wsgi/wsgi_server.py
odoo_wsgi/addons/web_shell/__init__.py
odoo_wsgi/addons/web_shell/__manifest__.py
odoo_wsgi/addons/web_shell/console.py
odoo_wsgi/addons/web_shell/ipt.py
odoo_wsgi/addons/web_shell/shell.py
odoo_wsgi/addons/web_shell/worker.py
odoo_wsgi/addons/web_shell/controllers/__init__.py
odoo_wsgi/addons/web_shell/controllers/main.py
odoo_wsgi/addons/web_shell/models/__init__.py
odoo_wsgi/addons/web_shell/models/models.py
odoo_wsgi-1.0.0.dist-info/METADATA
odoo_wsgi-1.0.0.dist-info/WHEEL
odoo_wsgi-1.0.0.dist-info/entry_points.txt
odoo_wsgi-1.0.0.dist-info/top_level.txt
odoo_wsgi-1.0.0.dist-info/RECORD
